fluentfs/__init__.py
fluentfs/common/__init__.py
fluentfs/common/functional.py
fluentfs/common/regex.py
fluentfs/common/s.py
fluentfs/common/table.py
fluentfs/exceptions/__init__.py
fluentfs/exceptions/exceptions.py
fluentfs/filelike/__init__.py
fluentfs/filelike/circular.py
fluentfs/filelike/dir.py
fluentfs/filelike/file.py
fluentfs/filelike/file_iterator.py
fluentfs/filelike/file_like.py
fluentfs/filelike/sym_link.py
fluentfs/filelike/text_file.py
fluentfs/filelike/text_file_iterator.py
fluentfs/filesize/__init__.py
fluentfs/filesize/file_size.py
fluentfs/filesize/file_size_unit.py
fluentfs/paths/__init__.py
fluentfs/paths/matches.py
fluentfs/paths/paths.py
test/__init__.py
test/test_fs_values.py
test/common/__init__.py
test/common/examples/__init__.py
test/common/examples/test_examples.py
test/common/examples/test_readme.py
test/common/modules/__init__.py
test/common/modules/common/__init__.py
test/common/modules/common/test_functional.py
test/common/modules/common/test_s.py
test/common/modules/common/test_table.py
test/common/modules/filelike/__init__.py
test/common/modules/filelike/test_dir.py
test/common/modules/filelike/test_file.py
test/common/modules/filelike/test_file_iterator.py
test/common/modules/filelike/test_sym_link.py
test/common/modules/filelike/test_text_file.py
test/common/modules/filesize/__init__.py
test/common/modules/filesize/test_file_size.py
test/common/modules/filesize/test_file_size_unit.py
test/common/modules/paths/__init__.py
test/common/modules/paths/test_matches.py
test/common/modules/paths/test_paths.py
test/posix/__init__.py
test/posix/test_norm_posix.py
test/win/__init__.py
test/win/test_norm_win.py
fluentfs-0.4.0.dist-info/LICENSE
fluentfs-0.4.0.dist-info/METADATA
fluentfs-0.4.0.dist-info/WHEEL
fluentfs-0.4.0.dist-info/top_level.txt
fluentfs-0.4.0.dist-info/RECORD
