Metadata-Version: 2.1
Name: fluentfs
Version: 0.4.0
Summary: Functional and fluent interface for filesystem interactions
Home-page: https://github.com/uhasker/fluentfs
Author: uhasker
Author-email: uhasker@protonmail.com
License: MIT
License-File: LICENSE
